examples/async/async_main.py
examples/sync/sync_main.py
venv/bin/activate_this.py
whissle/__init__.py
whissle/client.py
whissle/models.py
whissle/options.py
whissle/clients/__init__.py
whissle/clients/async_client.py
whissle/clients/client.py
whissle/clients/errors.py
whissle/clients/utils.py
whissle-0.0.1.dist-info/licenses/LICENSE
whissle-0.0.1.dist-info/METADATA
whissle-0.0.1.dist-info/WHEEL
whissle-0.0.1.dist-info/top_level.txt
whissle-0.0.1.dist-info/RECORD
