Metadata-Version: 2.4
Name: whissle
Version: 0.0.1
Summary: Python SDK for Whissle API.
Author-email: Nihar Sanda <nsanda@whissle.ai>
License:                     GNU GENERAL PUBLIC LICENSE
Project-URL: homepath, https://github.com/WhissleAI
Project-URL: documentation, https://github.com/WhissleAI
Project-URL: repository, https://github.com/WhissleAI
Keywords: stt,tts,streaming,real-time
Classifier: Development Status :: 3 - Alpha
Classifier: Intended Audience :: Developers
Classifier: Intended Audience :: Science/Research
Classifier: License :: OSI Approved :: MIT License
Classifier: Natural Language :: English
Classifier: Topic :: Scientific/Engineering :: Artificial Intelligence
Classifier: Topic :: Software Development :: Libraries
Classifier: Topic :: Software Development :: Libraries :: Python Modules
Classifier: Programming Language :: Python :: 3
Classifier: Programming Language :: Python :: 3.8
Classifier: Programming Language :: Python :: 3.9
Classifier: Programming Language :: Python :: 3.10
Classifier: Programming Language :: Python :: 3.11
Requires-Python: >3.8
License-File: LICENSE
Requires-Dist: python-dotenv
Requires-Dist: pydantic
Requires-Dist: httpx
Provides-Extra: all
Requires-Dist: pre-commit; extra == "all"
Requires-Dist: ruff; extra == "all"
Requires-Dist: python-dotenv; extra == "all"
Requires-Dist: pydantic; extra == "all"
Requires-Dist: httpx; extra == "all"
Provides-Extra: dev
Requires-Dist: pre-commit; extra == "dev"
Requires-Dist: ruff; extra == "dev"
Dynamic: license-file
